src/mac.sv
module mac(
    input logic clk,
    input logic rst,
    input logic en, //need?
    input logic [15:0] A,
    input logic [15:0] B,
    input logic valid,
    output logic [31:0] acc,
    output logic [15:0] A_out,
    output logic [15:0] B_out,
    output logic valid_out
);

    logic [31:0] mult1;
    logic [2:0] valid_shift;

    always_ff @(posedge clk or negedge rst) begin //ASIC might have to change setup
        if(~rst) begin
            //blah
            mult1 <= 32'd0;
            acc <= 32'd0;
            A_out <= 16'd0;
            B_out <= 16'd0;
            valid_out <= 1'b0;
            valid_shift <= 0;
        end else begin
            if(en) begin
                A_out <= A;
                B_out <= B;
                valid_shift <= {valid_shift[1:0], valid};
                if(|valid_shift) begin
                    mult1 <= A * B; //CHECK if fpga has MAC in DS 
                    if(valid_shift[2]) begin
                        acc <= mult1 + acc;
                        valid_shift <= 0;
                        valid_out <= 1'b1;
                    end else 
                        valid_out <= 1'b0;
                end else
                    valid_out <= 1'b0;
            end else begin
                A_out <= A_out;
                B_out <= B_out;
                valid_out <= valid_out;
            end
        end
    end
endmodule

src/systolic.sv
module systolic #(parameter N = 3)(
    input logic clk,
    input logic rst,
    input logic en, //need?
    input logic [15:0] A_row [N - 1:0],
    input logic [15:0] B_col [N - 1:0],
    output logic [31:0] result [N-1:0][N-1:0],
    output logic result_valid
);

    /*mac zerozero(.clk(clk), .rst(rst), .en(open), .A(), .B(B_out), .valid(), .acc(), .A_out(), .B_out(), .valid_out());
    mac zeroone(.clk(clk), .rst(rst), .en(open), .A(), .B(B_out), .valid(), .acc(), .A_out(), .B_out(), .valid_out());
    mac onezero(.clk(clk), .rst(rst), .en(open), .A(), .B(B_out), .valid(), .acc(), .A_out(), .B_out(), .valid_out());
    mac oneone (.clk(clk), .rst(rst), .en(open), .A(), .B(B_out), .valid(), .acc(), .A_out(), .B_out(), .valid_out());*/

    logic [N*N : 0] valid_bits;
    logic [15:0] A_pass [(N*N)];
    logic [15:0] B_pass [(N*N)];

    logic [31:0] acc_arr [N - 1:0][N - 1:0];
    assign result_valid = valid_bits[(N*N)];
    assign result = acc_arr;

    genvar k;
    generate
        for(k = 0; k < (N*N); k = k + 1) begin : FULL_SYSTOLIC

        /*for(i = 0; i < N; i = i + 1) begin : SYSTOLIC_ROW
            for(j = 0; j < N; j = j + 1) begin : SYSTOLIC_COL*/
                logic [31:0] acc;
                //Control
                /*always@(posedge clk or negedge rst) begin 
                    if(~rst) begin
                    end else if() begin

                    end
                end*/

                //Datapath
                if(k == 0) begin
                    mac left_col(.clk(clk), .rst(rst), .en(en), .A(A_row[0]), .B(B_col[0]), .valid(1), .acc(acc_arr[0][0]), .A_out(A_pass[0]), .B_out(B_pass[0]), .valid_out(valid_bits[k]));
                end
                else if(k%N == 0) begin
                    mac left_col(.clk(clk), .rst(rst), .en(en), .A(A_row[k/N]), .B(B_pass[k-N]), .valid(valid_bits[k-1]), .acc(acc_arr[k/N][k%N]), .A_out(A_pass[k]), .B_out(B_pass[k]), .valid_out(valid_bits[k]));
                end else if(k < N) begin
                    mac top_row(.clk(clk), .rst(rst), .en(en), .A(A_pass[k-1]), .B(B_col[k%N]), .valid(valid_bits[k-1]), .acc(acc_arr[k/N][k%N]), .A_out(A_pass[k]), .B_out(B_pass[k]), .valid_out(valid_bits[k]));
                end else begin
                    mac filler(.clk(clk), .rst(rst), .en(en), .A(A_pass[k-1]), .B(B_pass[k-N]), .valid(valid_bits[k-1]), .acc(acc_arr[k/N][k%N]), .A_out(A_pass[k]), .B_out(B_pass[k]), .valid_out(valid_bits[k]));
                end
        end
            /*end  
        end*/
    endgenerate

endmodule

src/control.sv
module control #(parameter N = 3)(
    input logic clk,
    input logic rst,
    input logic en,
    input logic [15:0] A [N - 1:0][N - 1:0],
    input logic [15:0] B [N - 1:0][N - 1:0],
    output logic [31:0] result [N - 1:0][N - 1:0],
    output logic result_valid
);
    logic [15:0] A_row [N - 1:0];
    logic [15:0] B_col [N - 1:0];
    logic [2:0] divider;
    //logic [31:0] result [N - 1:0][N - 1:0];

    logic [$clog2(N)-1:0] count;

    systolic array(.clk(clk), .rst(rst), .en(en), .A_row(A_row), .B_col(B_col), .result(result), .result_valid(result_valid));

    always @(posedge clk or negedge rst) begin
        if(~rst) begin
            count <= -1;
            divider <= 0;
            //result_valid <= 1'b0;
            for(int i = 0; i < N; i++)
                for(int j = 0; j < N; j++)
                    result[i][j] <= 32'b0;

        end else begin
            if(divider == 2) begin
                count <= count + 1; 
                divider <= 0;
            end else begin
                divider <= divider + 1;
            end

            for(int i = 0; i < N; i++) begin
                A_row[i] = A[count][i];
                B_col[i] = B[i][count];
            end
        end
    end



endmodule

testbench/control_tb.sv
module control_tb(); 
    logic clk, rst, result_valid, en, counter_en;
    logic [15:0] A [2:0][2:0];
    logic [15:0] B [2:0][2:0];
    logic [31:0] result [2:0][2:0];
    logic [99:0] counter;
    
    control dut(.clk(clk), .rst(rst), .A(A), .B(B), .result(result), .result_valid(result_valid), .en(en));

    initial begin
        $dumpfile ("waves/control_tb.vcd");
        $dumpvars(0, control_tb);  

        forever #10 clk = ~clk;
    end

    task reset();
        begin
            clk = 1'b0;
            //result_valid = 1'b0;
            en = 1'b0;
            rst = 1'b1;
            @(posedge clk);
            @(posedge clk);
            rst = 1'b0;
            @(posedge clk);
            @(posedge clk);
            rst = 1'b1;
            @(posedge clk);
            @(posedge clk);
            counter = 0;
            counter_en = 0;
        end
    endtask

    task test1();
        begin
            // Manual assignment for Matrix A
            A[0][0] = 5;   A[0][1] = 12;  A[0][2] = 7;
            A[1][0] = 3;   A[1][1] = 8;   A[1][2] = 1;
            A[2][0] = 6;   A[2][1] = 2;   A[2][2] = 4;

            // Manual assignment for Matrix B
            B[0][0] = 1;   B[0][1] = 3;   B[0][2] = 5;
            B[1][0] = 2;   B[1][1] = 7;   B[1][2] = 0;
            B[2][0] = 4;   B[2][1] = 6;   B[2][2] = 8;

            // Optional: print matrices to verify
            $display("Matrix A:");
            $display("%0d %0d %0d", A[0][0], A[0][1], A[0][2]);
            $display("%0d %0d %0d", A[1][0], A[1][1], A[1][2]);
            $display("%0d %0d %0d", A[2][0], A[2][1], A[2][2]);

            $display("Matrix B:");
            $display("%0d %0d %0d", B[0][0], B[0][1], B[0][2]);
            $display("%0d %0d %0d", B[1][0], B[1][1], B[1][2]);
            $display("%0d %0d %0d", B[2][0], B[2][1], B[2][2]);
            en = 1'b1;
            counter_en = 1'b1;

            $display("BLAH BLAH");
        end
    endtask

    initial begin
        reset();
        test1();
    end

    always_ff @(posedge clk) begin
            if(counter_en) begin
                counter <= counter + 1;
                $display("CYCLE \n");
                $display("%0d %0d %0d", result[0][0], result[0][1], result[0][2]);
                $display("%0d %0d %0d", result[1][0], result[1][1], result[1][2]);
                $display("%0d %0d %0d", result[2][0], result[2][1], result[2][2]);
            end
            if(counter > 95) begin
                counter_en = 1'b0;
                $finish;
            end
    end

endmodule

waves/control_tb.vcd
$version Generated by VerilatedVcd $end
$timescale 1ps $end
 $scope module TOP $end
  $scope module control_tb $end
   $var wire 1 N! clk $end
   $var wire 1 # rst $end
   $var wire 1 7 result_valid $end
   $var wire 1 $ en $end
   $var wire 1 O! counter_en $end
   $var wire 16 % A[0][0] [15:0] $end
   $var wire 16 & A[0][1] [15:0] $end
   $var wire 16 ' A[0][2] [15:0] $end
   $var wire 16 ( A[1][0] [15:0] $end
   $var wire 16 ) A[1][1] [15:0] $end
   $var wire 16 * A[1][2] [15:0] $end
   $var wire 16 + A[2][0] [15:0] $end
   $var wire 16 , A[2][1] [15:0] $end
   $var wire 16 - A[2][2] [15:0] $end
   $var wire 16 . B[0][0] [15:0] $end
   $var wire 16 / B[0][1] [15:0] $end
   $var wire 16 0 B[0][2] [15:0] $end
   $var wire 16 1 B[1][0] [15:0] $end
   $var wire 16 2 B[1][1] [15:0] $end
   $var wire 16 3 B[1][2] [15:0] $end
   $var wire 16 4 B[2][0] [15:0] $end
   $var wire 16 5 B[2][1] [15:0] $end
   $var wire 16 6 B[2][2] [15:0] $end
   $var wire 32 E! result[0][0] [31:0] $end
   $var wire 32 F! result[0][1] [31:0] $end
   $var wire 32 G! result[0][2] [31:0] $end
   $var wire 32 H! result[1][0] [31:0] $end
   $var wire 32 I! result[1][1] [31:0] $end
   $var wire 32 J! result[1][2] [31:0] $end
   $var wire 32 K! result[2][0] [31:0] $end
   $var wire 32 L! result[2][1] [31:0] $end
   $var wire 32 M! result[2][2] [31:0] $end
   $var wire 100 P! counter [99:0] $end
   $scope module dut $end
    $var wire 32 T! N [31:0] $end
    $var wire 1 N! clk $end
    $var wire 1 # rst $end
    $var wire 1 $ en $end
    $var wire 16 % A[0][0] [15:0] $end
    $var wire 16 & A[0][1] [15:0] $end
    $var wire 16 ' A[0][2] [15:0] $end
    $var wire 16 ( A[1][0] [15:0] $end
    $var wire 16 ) A[1][1] [15:0] $end
    $var wire 16 * A[1][2] [15:0] $end
    $var wire 16 + A[2][0] [15:0] $end
    $var wire 16 , A[2][1] [15:0] $end
    $var wire 16 - A[2][2] [15:0] $end
    $var wire 16 . B[0][0] [15:0] $end
    $var wire 16 / B[0][1] [15:0] $end
    $var wire 16 0 B[0][2] [15:0] $end
    $var wire 16 1 B[1][0] [15:0] $end
    $var wire 16 2 B[1][1] [15:0] $end
    $var wire 16 3 B[1][2] [15:0] $end
    $var wire 16 4 B[2][0] [15:0] $end
    $var wire 16 5 B[2][1] [15:0] $end
    $var wire 16 6 B[2][2] [15:0] $end
    $var wire 32 E! result[0][0] [31:0] $end
    $var wire 32 F! result[0][1] [31:0] $end
    $var wire 32 G! result[0][2] [31:0] $end
    $var wire 32 H! result[1][0] [31:0] $end
    $var wire 32 I! result[1][1] [31:0] $end
    $var wire 32 J! result[1][2] [31:0] $end
    $var wire 32 K! result[2][0] [31:0] $end
    $var wire 32 L! result[2][1] [31:0] $end
    $var wire 32 M! result[2][2] [31:0] $end
    $var wire 1 7 result_valid $end
    $var wire 16 8 A_row[0] [15:0] $end
    $var wire 16 9 A_row[1] [15:0] $end
    $var wire 16 : A_row[2] [15:0] $end
    $var wire 16 ; B_col[0] [15:0] $end
    $var wire 16 < B_col[1] [15:0] $end
    $var wire 16 = B_col[2] [15:0] $end
    $var wire 3 > divider [2:0] $end
    $var wire 2 ? count [1:0] $end
    $scope module array $end
     $var wire 32 T! N [31:0] $end
     $var wire 1 N! clk $end
     $var wire 1 # rst $end
     $var wire 1 $ en $end
     $var wire 16 8 A_row[0] [15:0] $end
     $var wire 16 9 A_row[1] [15:0] $end
     $var wire 16 : A_row[2] [15:0] $end
     $var wire 16 ; B_col[0] [15:0] $end
     $var wire 16 < B_col[1] [15:0] $end
     $var wire 16 = B_col[2] [15:0] $end
     $var wire 32 E! result[0][0] [31:0] $end
     $var wire 32 F! result[0][1] [31:0] $end
     $var wire 32 G! result[0][2] [31:0] $end
     $var wire 32 H! result[1][0] [31:0] $end
     $var wire 32 I! result[1][1] [31:0] $end
     $var wire 32 J! result[1][2] [31:0] $end
     $var wire 32 K! result[2][0] [31:0] $end
     $var wire 32 L! result[2][1] [31:0] $end
     $var wire 32 M! result[2][2] [31:0] $end
     $var wire 1 7 result_valid $end
     $var wire 10 @ valid_bits [9:0] $end
     $var wire 16 A A_pass[0] [15:0] $end
     $var wire 16 B A_pass[1] [15:0] $end
     $var wire 16 C A_pass[2] [15:0] $end
     $var wire 16 D A_pass[3] [15:0] $end
     $var wire 16 E A_pass[4] [15:0] $end
     $var wire 16 F A_pass[5] [15:0] $end
     $var wire 16 G A_pass[6] [15:0] $end
     $var wire 16 H A_pass[7] [15:0] $end
     $var wire 16 I A_pass[8] [15:0] $end
     $var wire 16 J B_pass[0] [15:0] $end
     $var wire 16 K B_pass[1] [15:0] $end
     $var wire 16 L B_pass[2] [15:0] $end
     $var wire 16 M B_pass[3] [15:0] $end
     $var wire 16 N B_pass[4] [15:0] $end
     $var wire 16 O B_pass[5] [15:0] $end
     $var wire 16 P B_pass[6] [15:0] $end
     $var wire 16 Q B_pass[7] [15:0] $end
     $var wire 16 R B_pass[8] [15:0] $end
     $var wire 32 S acc_arr[0][0] [31:0] $end
     $var wire 32 T acc_arr[0][1] [31:0] $end
     $var wire 32 U acc_arr[0][2] [31:0] $end
     $var wire 32 V acc_arr[1][0] [31:0] $end
     $var wire 32 W acc_arr[1][1] [31:0] $end
     $var wire 32 X acc_arr[1][2] [31:0] $end
     $var wire 32 Y acc_arr[2][0] [31:0] $end
     $var wire 32 Z acc_arr[2][1] [31:0] $end
     $var wire 32 [ acc_arr[2][2] [31:0] $end
     $scope module FULL_SYSTOLIC[0] $end
      $var wire 32 U! acc [31:0] $end
      $scope module genblk1 $end
       $scope module left_col $end
        $var wire 1 N! clk $end
        $var wire 1 # rst $end
        $var wire 1 $ en $end
        $var wire 16 \ A [15:0] $end
        $var wire 16 ] B [15:0] $end
        $var wire 1 V! valid $end
        $var wire 32 ^ acc [31:0] $end
        $var wire 16 _ A_out [15:0] $end
        $var wire 16 ` B_out [15:0] $end
        $var wire 1 a valid_out $end
        $var wire 32 b mult1 [31:0] $end
        $var wire 3 c valid_shift [2:0] $end
       $upscope $end
      $upscope $end
     $upscope $end
     $scope module FULL_SYSTOLIC[1] $end
      $var wire 32 W! acc [31:0] $end
      $scope module genblk1 $end
       $scope module top_row $end
        $var wire 1 N! clk $end
        $var wire 1 # rst $end
        $var wire 1 $ en $end
        $var wire 16 _ A [15:0] $end
        $var wire 16 d B [15:0] $end
        $var wire 1 e valid $end
        $var wire 32 f acc [31:0] $end
        $var wire 16 g A_out [15:0] $end
        $var wire 16 h B_out [15:0] $end
        $var wire 1 i valid_out $end
        $var wire 32 j mult1 [31:0] $end
        $var wire 3 k valid_shift [2:0] $end
       $upscope $end
      $upscope $end
     $upscope $end
     $scope module FULL_SYSTOLIC[2] $end
      $var wire 32 X! acc [31:0] $end
      $scope module genblk1 $end
       $scope module top_row $end
        $var wire 1 N! clk $end
        $var wire 1 # rst $end
        $var wire 1 $ en $end
        $var wire 16 g A [15:0] $end
        $var wire 16 l B [15:0] $end
        $var wire 1 m valid $end
        $var wire 32 n acc [31:0] $end
        $var wire 16 o A_out [15:0] $end
        $var wire 16 p B_out [15:0] $end
        $var wire 1 q valid_out $end
        $var wire 32 r mult1 [31:0] $end
        $var wire 3 s valid_shift [2:0] $end
       $upscope $end
      $upscope $end
     $upscope $end
     $scope module FULL_SYSTOLIC[3] $end
      $var wire 32 Y! acc [31:0] $end
      $scope module genblk1 $end
       $scope module left_col $end
        $var wire 1 N! clk $end
        $var wire 1 # rst $end
        $var wire 1 $ en $end
        $var wire 16 t A [15:0] $end
        $var wire 16 ` B [15:0] $end
        $var wire 1 u valid $end
        $var wire 32 v acc [31:0] $end
        $var wire 16 w A_out [15:0] $end
        $var wire 16 x B_out [15:0] $end
        $var wire 1 y valid_out $end
        $var wire 32 z mult1 [31:0] $end
        $var wire 3 { valid_shift [2:0] $end
       $upscope $end
      $upscope $end
     $upscope $end
     $scope module FULL_SYSTOLIC[4] $end
      $var wire 32 Z! acc [31:0] $end
      $scope module genblk1 $end
       $scope module filler $end
        $var wire 1 N! clk $end
        $var wire 1 # rst $end
        $var wire 1 $ en $end
        $var wire 16 w A [15:0] $end
        $var wire 16 h B [15:0] $end
        $var wire 1 | valid $end
        $var wire 32 } acc [31:0] $end
        $var wire 16 ~ A_out [15:0] $end
        $var wire 16 !! B_out [15:0] $end
        $var wire 1 "! valid_out $end
        $var wire 32 #! mult1 [31:0] $end
        $var wire 3 $! valid_shift [2:0] $end
       $upscope $end
      $upscope $end
     $upscope $end
     $scope module FULL_SYSTOLIC[5] $end
      $var wire 32 [! acc [31:0] $end
      $scope module genblk1 $end
       $scope module filler $end
        $var wire 1 N! clk $end
        $var wire 1 # rst $end
        $var wire 1 $ en $end
        $var wire 16 ~ A [15:0] $end
        $var wire 16 p B [15:0] $end
        $var wire 1 %! valid $end
        $var wire 32 &! acc [31:0] $end
        $var wire 16 '! A_out [15:0] $end
        $var wire 16 (! B_out [15:0] $end
        $var wire 1 )! valid_out $end
        $var wire 32 *! mult1 [31:0] $end
        $var wire 3 +! valid_shift [2:0] $end
       $upscope $end
      $upscope $end
     $upscope $end
     $scope module FULL_SYSTOLIC[6] $end
      $var wire 32 \! acc [31:0] $end
      $scope module genblk1 $end
       $scope module left_col $end
        $var wire 1 N! clk $end
        $var wire 1 # rst $end
        $var wire 1 $ en $end
        $var wire 16 ,! A [15:0] $end
        $var wire 16 x B [15:0] $end
        $var wire 1 -! valid $end
        $var wire 32 .! acc [31:0] $end
        $var wire 16 /! A_out [15:0] $end
        $var wire 16 0! B_out [15:0] $end
        $var wire 1 1! valid_out $end
        $var wire 32 2! mult1 [31:0] $end
        $var wire 3 3! valid_shift [2:0] $end
       $upscope $end
      $upscope $end
     $upscope $end
     $scope module FULL_SYSTOLIC[7] $end
      $var wire 32 ]! acc [31:0] $end
      $scope module genblk1 $end
       $scope module filler $end
        $var wire 1 N! clk $end
        $var wire 1 # rst $end
        $var wire 1 $ en $end
        $var wire 16 /! A [15:0] $end
        $var wire 16 !! B [15:0] $end
        $var wire 1 4! valid $end
        $var wire 32 5! acc [31:0] $end
        $var wire 16 6! A_out [15:0] $end
        $var wire 16 7! B_out [15:0] $end
        $var wire 1 8! valid_out $end
        $var wire 32 9! mult1 [31:0] $end
        $var wire 3 :! valid_shift [2:0] $end
       $upscope $end
      $upscope $end
     $upscope $end
     $scope module FULL_SYSTOLIC[8] $end
      $var wire 32 ^! acc [31:0] $end
      $scope module genblk1 $end
       $scope module filler $end
        $var wire 1 N! clk $end
        $var wire 1 # rst $end
        $var wire 1 $ en $end
        $var wire 16 6! A [15:0] $end
        $var wire 16 (! B [15:0] $end
        $var wire 1 ;! valid $end
        $var wire 32 <! acc [31:0] $end
        $var wire 16 =! A_out [15:0] $end
        $var wire 16 >! B_out [15:0] $end
        $var wire 1 ?! valid_out $end
        $var wire 32 @! mult1 [31:0] $end
        $var wire 3 A! valid_shift [2:0] $end
       $upscope $end
      $upscope $end
     $upscope $end
    $upscope $end
    $scope module unnamedblk1 $end
     $var wire 32 B! i [31:0] $end
     $scope module unnamedblk2 $end
      $var wire 32 C! j [31:0] $end
     $upscope $end
    $upscope $end
    $scope module unnamedblk3 $end
     $var wire 32 D! i [31:0] $end
    $upscope $end
   $upscope $end
  $upscope $end
 $upscope $end
$enddefinitions $end


#0
1#
0$
b0000000000000000 %
b0000000000000000 &
b0000000000000000 '
b0000000000000000 (
b0000000000000000 )
b0000000000000000 *
b0000000000000000 +
b0000000000000000 ,
b0000000000000000 -
b0000000000000000 .
b0000000000000000 /
b0000000000000000 0
b0000000000000000 1
b0000000000000000 2
b0000000000000000 3
b0000000000000000 4
b0000000000000000 5
b0000000000000000 6
07
b0000000000000000 8
b0000000000000000 9
b0000000000000000 :
b0000000000000000 ;
b0000000000000000 <
b0000000000000000 =
b000 >
b00 ?
b0000000000 @
b0000000000000000 A
b0000000000000000 B
b0000000000000000 C
b0000000000000000 D
b0000000000000000 E
b0000000000000000 F
b0000000000000000 G
b0000000000000000 H
b0000000000000000 I
b0000000000000000 J
b0000000000000000 K
b0000000000000000 L
b0000000000000000 M
b0000000000000000 N
b0000000000000000 O
b0000000000000000 P
b0000000000000000 Q
b0000000000000000 R
b00000000000000000000000000000000 S
b00000000000000000000000000000000 T
b00000000000000000000000000000000 U
b00000000000000000000000000000000 V
b00000000000000000000000000000000 W
b00000000000000000000000000000000 X
b00000000000000000000000000000000 Y
b00000000000000000000000000000000 Z
b00000000000000000000000000000000 [
b0000000000000000 \
b0000000000000000 ]
b00000000000000000000000000000000 ^
b0000000000000000 _
b0000000000000000 `
0a
b00000000000000000000000000000000 b
b000 c
b0000000000000000 d
0e
b00000000000000000000000000000000 f
b0000000000000000 g
b0000000000000000 h
0i
b00000000000000000000000000000000 j
b000 k
b0000000000000000 l
0m
b00000000000000000000000000000000 n
b0000000000000000 o
b0000000000000000 p
0q
b00000000000000000000000000000000 r
b000 s
b0000000000000000 t
0u
b00000000000000000000000000000000 v
b0000000000000000 w
b0000000000000000 x
0y
b00000000000000000000000000000000 z
b000 {
0|
b00000000000000000000000000000000 }
b0000000000000000 ~
b0000000000000000 !!
0"!
b00000000000000000000000000000000 #!
b000 $!
0%!
b00000000000000000000000000000000 &!
b0000000000000000 '!
b0000000000000000 (!
0)!
b00000000000000000000000000000000 *!
b000 +!
b0000000000000000 ,!
0-!
b00000000000000000000000000000000 .!
b0000000000000000 /!
b0000000000000000 0!
01!
b00000000000000000000000000000000 2!
b000 3!
04!
b00000000000000000000000000000000 5!
b0000000000000000 6!
b0000000000000000 7!
08!
b00000000000000000000000000000000 9!
b000 :!
0;!
b00000000000000000000000000000000 <!
b0000000000000000 =!
b0000000000000000 >!
0?!
b00000000000000000000000000000000 @!
b000 A!
b00000000000000000000000000000000 B!
b00000000000000000000000000000000 C!
b00000000000000000000000000000000 D!
b00000000000000000000000000000000 E!
b00000000000000000000000000000000 F!
b00000000000000000000000000000000 G!
b00000000000000000000000000000000 H!
b00000000000000000000000000000000 I!
b00000000000000000000000000000000 J!
b00000000000000000000000000000000 K!
b00000000000000000000000000000000 L!
b00000000000000000000000000000000 M!
0N!
0O!
b0000000000000000000000000000000000000000000000000000000000000000000000000000000000000000000000000000 P!
b00000000000000000000000000000011 T!
b00000000000000000000000000000000 U!
1V!
b00000000000000000000000000000000 W!
b00000000000000000000000000000000 X!
b00000000000000000000000000000000 Y!
b00000000000000000000000000000000 Z!
b00000000000000000000000000000000 [!
b00000000000000000000000000000000 \!
b00000000000000000000000000000000 ]!
b00000000000000000000000000000000 ^!
#10
b001 >
b00000000000000000000000000000011 D!
1N!
#20
0N!
#30
0#
b000 >
b11 ?
b00000000000000000000000000000011 B!
b00000000000000000000000000000011 C!
1N!
#40
0N!
#50
1N!
#60
0N!
#70
1#
b001 >
1N!
#80
0N!
#90
b010 >
1N!
#100
0N!
#110
1$
b0000000000000101 %
b0000000000001100 &
b0000000000000111 '
b0000000000000011 (
b0000000000001000 )
b0000000000000001 *
b0000000000000110 +
b0000000000000010 ,
b0000000000000100 -
b0000000000000001 .
b0000000000000011 /
b0000000000000101 0
b0000000000000010 1
b0000000000000111 2
b0000000000000100 4
b0000000000000110 5
b0000000000001000 6
b0000000000000101 8
b0000000000001100 9
b0000000000000111 :
b000 >
b00 ?
b0000000000000101 A
b0000000000001100 D
b0000000000000111 G
b0000000000000101 \
b0000000000000101 _
b001 c
b0000000000001100 t
b0000000000001100 w
b0000000000000111 ,!
b0000000000000111 /!
1N!
1O!
b0000000000000000000000000000000000000000000000000000000000000000000000000000000000000000000000000001 P!
#120
0N!
#130
b0000000000000001 ;
b0000000000000010 <
b0000000000000100 =
b001 >
b0000000000000101 B
b0000000000001100 E
b0000000000000111 H
b0000000000000001 J
b0000000000000010 K
b0000000000000100 L
b0000000000000001 ]
b0000000000000001 `
b00000000000000000000000000000101 b
b011 c
b0000000000000010 d
b0000000000000101 g
b0000000000000010 h
b0000000000000100 l
b0000000000000100 p
b0000000000001100 ~
b0000000000000111 6!
1N!
b0000000000000000000000000000000000000000000000000000000000000000000000000000000000000000000000000010 P!
#140
0N!
#150
b010 >
b0000000000000101 C
b0000000000001100 F
b0000000000000111 I
b0000000000000001 M
b0000000000000010 N
b0000000000000100 O
b111 c
b0000000000000101 o
b0000000000000001 x
b0000000000000010 !!
b0000000000001100 '!
b0000000000000100 (!
b0000000000000111 =!
1N!
b0000000000000000000000000000000000000000000000000000000000000000000000000000000000000000000000000011 P!
#160
0N!
#170
b000 >
b01 ?
b0000000001 @
b0000000000000001 P
b0000000000000010 Q
b0000000000000100 R
b00000000000000000000000000000101 S
b00000000000000000000000000000101 ^
1a
b000 c
1e
b0000000000000001 0!
b0000000000000010 7!
b0000000000000100 >!
b00000000000000000000000000000101 E!
1N!
b0000000000000000000000000000000000000000000000000000000000000000000000000000000000000000000000000100 P!
#180
0N!
#190
b0000000000000011 8
b0000000000001000 9
b0000000000000001 :
b0000000000000011 ;
b0000000000000111 <
b0000000000000110 =
b001 >
b0000000000 @
b0000000000000011 A
b0000000000001000 D
b0000000000000001 G
b0000000000000011 J
b0000000000000111 K
b0000000000000110 L
b0000000000000011 \
b0000000000000011 ]
b0000000000000011 _
b0000000000000011 `
0a
b001 c
b0000000000000111 d
0e
b0000000000000111 h
b001 k
b0000000000000110 l
b0000000000000110 p
b0000000000001000 t
b0000000000001000 w
b0000000000000001 ,!
b0000000000000001 /!
1N!
b0000000000000000000000000000000000000000000000000000000000000000000000000000000000000000000000000101 P!
#200
0N!
#210
b010 >
b0000000000000011 B
b0000000000001000 E
b0000000000000001 H
b0000000000000011 M
b0000000000000111 N
b0000000000000110 O
b00000000000000000000000000001001 b
b011 c
b0000000000000011 g
b00000000000000000000000000010101 j
b010 k
b0000000000000011 x
b0000000000001000 ~
b0000000000000111 !!
b0000000000000110 (!
b0000000000000001 6!
1N!
b0000000000000000000000000000000000000000000000000000000000000000000000000000000000000000000000000110 P!
#220
0N!
#230
b000 >
b10 ?
b0000000000000011 C
b0000000000001000 F
b0000000000000001 I
b0000000000000011 P
b0000000000000111 Q
b0000000000000110 R
b111 c
b100 k
b0000000000000011 o
b0000000000001000 '!
b0000000000000011 0!
b0000000000000111 7!
b0000000000000001 =!
b0000000000000110 >!
1N!
b0000000000000000000000000000000000000000000000000000000000000000000000000000000000000000000000000111 P!
#240
0N!
#250
b0000000000000110 8
b0000000000000010 9
b0000000000000100 :
b0000000000000101 ;
b0000000000000000 <
b0000000000001000 =
b001 >
b0000000011 @
b0000000000000110 A
b0000000000000010 D
b0000000000000100 G
b0000000000000101 J
b0000000000000000 K
b0000000000001000 L
b00000000000000000000000000001110 S
b00000000000000000000000000010101 T
b0000000000000110 \
b0000000000000101 ]
b00000000000000000000000000001110 ^
b0000000000000110 _
b0000000000000101 `
1a
b00000000000000000000000000011110 b
b000 c
b0000000000000000 d
1e
b00000000000000000000000000010101 f
b0000000000000000 h
1i
b00000000000000000000000000000000 j
b000 k
b0000000000001000 l
1m
b0000000000001000 p
b0000000000000010 t
b0000000000000010 w
b0000000000000100 ,!
b0000000000000100 /!
b00000000000000000000000000001110 E!
b00000000000000000000000000010101 F!
1N!
b0000000000000000000000000000000000000000000000000000000000000000000000000000000000000000000000001000 P!
#260
0N!
#270
b010 >
b0000000000 @
b0000000000000110 B
b0000000000000010 E
b0000000000000100 H
b0000000000000101 M
b0000000000000000 N
b0000000000001000 O
0a
b001 c
0e
b0000000000000110 g
0i
b001 k
0m
b001 s
b0000000000000101 x
b0000000000000010 ~
b0000000000000000 !!
b0000000000001000 (!
b0000000000000100 6!
1N!
b0000000000000000000000000000000000000000000000000000000000000000000000000000000000000000000000001001 P!
#280
0N!
#290
b000 >
b11 ?
b0000000000000110 C
b0000000000000010 F
b0000000000000100 I
b0000000000000101 P
b0000000000000000 Q
b0000000000001000 R
b011 c
b010 k
b0000000000000110 o
b00000000000000000000000000110000 r
b010 s
b0000000000000010 '!
b0000000000000101 0!
b0000000000000000 7!
b0000000000000100 =!
b0000000000001000 >!
1N!
b0000000000000000000000000000000000000000000000000000000000000000000000000000000000000000000000001010 P!
#300
0N!
#310
b0000000000000101 8
b0000000000001100 9
b0000000000000111 :
b0000000000000000 ;
b0000000000000000 =
b001 >
b0000000000000101 A
b0000000000001100 D
b0000000000000111 G
b0000000000000000 J
b0000000000000000 L
b0000000000000101 \
b0000000000000000 ]
b0000000000000101 _
b0000000000000000 `
b00000000000000000000000000000000 b
b111 c
b100 k
b0000000000000000 l
b0000000000000000 p
b00000000000000000000000000000000 r
b100 s
b0000000000001100 t
b0000000000001100 w
b0000000000000111 ,!
b0000000000000111 /!
1N!
b0000000000000000000000000000000000000000000000000000000000000000000000000000000000000000000000001011 P!
#320
0N!
#330
b010 >
b0000000111 @
b0000000000000101 B
b0000000000001100 E
b0000000000000111 H
b0000000000000000 M
b0000000000000000 O
1a
b000 c
1e
b0000000000000101 g
1i
b000 k
1m
1q
b000 s
1u
b0000000000000000 x
b0000000000001100 ~
b0000000000000000 (!
b0000000000000111 6!
1N!
b0000000000000000000000000000000000000000000000000000000000000000000000000000000000000000000000001100 P!
#340
0N!
#350
b000 >
b00 ?
b0000000000 @
b0000000000000101 C
b0000000000001100 F
b0000000000000111 I
b0000000000000000 P
b0000000000000000 R
0a
b001 c
0e
0i
b001 k
0m
b0000000000000101 o
0q
b001 s
0u
b001 {
b0000000000001100 '!
b0000000000000000 0!
b0000000000000111 =!
b0000000000000000 >!
1N!
b0000000000000000000000000000000000000000000000000000000000000000000000000000000000000000000000001101 P!
#360
0N!
#370
b0000000000000001 ;
b0000000000000010 <
b0000000000000100 =
b001 >
b0000000000000001 J
b0000000000000010 K
b0000000000000100 L
b0000000000000001 ]
b0000000000000001 `
b00000000000000000000000000000101 b
b011 c
b0000000000000010 d
b0000000000000010 h
b00000000000000000000000000001010 j
b010 k
b0000000000000100 l
b0000000000000100 p
b00000000000000000000000000010100 r
b010 s
b010 {
1N!
b0000000000000000000000000000000000000000000000000000000000000000000000000000000000000000000000001110 P!
#380
0N!
#390
b010 >
b0000000000000001 M
b0000000000000010 N
b0000000000000100 O
b111 c
b100 k
b100 s
b0000000000000001 x
b00000000000000000000000000001100 z
b100 {
b0000000000000010 !!
b0000000000000100 (!
1N!
b0000000000000000000000000000000000000000000000000000000000000000000000000000000000000000000000001111 P!
#400
0N!
